django_facebook_pixel_code-0.0.2.dist-info/DESCRIPTION.rst
django_facebook_pixel_code-0.0.2.dist-info/METADATA
django_facebook_pixel_code-0.0.2.dist-info/RECORD
django_facebook_pixel_code-0.0.2.dist-info/WHEEL
django_facebook_pixel_code-0.0.2.dist-info/metadata.json
django_facebook_pixel_code-0.0.2.dist-info/top_level.txt
facebook_pixel_code/__init__.py
facebook_pixel_code/templates/fpc/fpc.html
facebook_pixel_code/templatetags/__init__.py
facebook_pixel_code/templatetags/fpc_tags.py
