Metadata-Version: 2.0
Name: django-facebook-pixel-code
Version: 0.0.2
Summary: Easily include your Facebook Pixel Code tag in your django site
Home-page: https://github.com/AlessioBazzanella/django-facebook-pixel-code.git
Author: Alessio Bazzanella
Author-email: alessio.bazzanella@me.com
License: MIT
Keywords: django generic-views
Platform: UNKNOWN
Classifier: Development Status :: 3 - Alpha
Classifier: Topic :: Utilities
Classifier: License :: OSI Approved :: MIT License
